{
  "id": "605210be-2db5-4ffd-8728-754cd0074245",
  "prevId": "00000000-0000-0000-0000-000000000000",
  "version": "7",
  "dialect": "postgresql",
  "tables": {
    "public.accounts": {
      "name": "accounts",
      "schema": "",
      "columns": {
        "userId": {
          "name": "userId",
          "type": "text",
          "primaryKey": false,
          "notNull": true
        },
        "type": {
          "name": "type",
          "type": "text",
          "primaryKey": false,
          "notNull": true
        },
        "provider": {
          "name": "provider",
          "type": "text",
          "primaryKey": false,
          "notNull": true
        },
        "providerAccountId": {
          "name": "providerAccountId",
          "type": "text",
          "primaryKey": false,
          "notNull": true
        },
        "refresh_token": {
          "name": "refresh_token",
          "type": "text",
          "primaryKey": false,
          "notNull": false
        },
        "access_token": {
          "name": "access_token",
          "type": "text",
          "primaryKey": false,
          "notNull": false
        },
        "expires_at": {
          "name": "expires_at",
          "type": "integer",
          "primaryKey": false,
          "notNull": false
        },
        "token_type": {
          "name": "token_type",
          "type": "text",
          "primaryKey": false,
          "notNull": false
        },
        "scope": {
          "name": "scope",
          "type": "text",
          "primaryKey": false,
          "notNull": false
        },
        "id_token": {
          "name": "id_token",
          "type": "text",
          "primaryKey": false,
          "notNull": false
        },
        "session_state": {
          "name": "session_state",
          "type": "text",
          "primaryKey": false,
          "notNull": false
        }
      },
      "indexes": {},
      "foreignKeys": {
        "accounts_userId_users_id_fk": {
          "name": "accounts_userId_users_id_fk",
          "tableFrom": "accounts",
          "tableTo": "users",
          "columnsFrom": [
            "userId"
          ],
          "columnsTo": [
            "id"
          ],
          "onDelete": "cascade",
          "onUpdate": "no action"
        }
      },
      "compositePrimaryKeys": {
        "accounts_provider_providerAccountId_pk": {
          "name": "accounts_provider_providerAccountId_pk",
          "columns": [
            "provider",
            "providerAccountId"
          ]
        }
      },
      "uniqueConstraints": {},
      "policies": {},
      "checkConstraints": {},
      "isRLSEnabled": false
    },
    "public.goal_contributions": {
      "name": "goal_contributions",
      "schema": "",
      "columns": {
        "id": {
          "name": "id",
          "type": "text",
          "primaryKey": true,
          "notNull": true
        },
        "goal_id": {
          "name": "goal_id",
          "type": "text",
          "primaryKey": false,
          "notNull": true
        },
        "month_key": {
          "name": "month_key",
          "type": "text",
          "primaryKey": false,
          "notNull": true
        },
        "amount": {
          "name": "amount",
          "type": "numeric(12, 2)",
          "primaryKey": false,
          "notNull": true
        },
        "note": {
          "name": "note",
          "type": "text",
          "primaryKey": false,
          "notNull": false
        },
        "created_at": {
          "name": "created_at",
          "type": "timestamp",
          "primaryKey": false,
          "notNull": true,
          "default": "now()"
        }
      },
      "indexes": {},
      "foreignKeys": {
        "goal_contributions_goal_id_savings_goals_id_fk": {
          "name": "goal_contributions_goal_id_savings_goals_id_fk",
          "tableFrom": "goal_contributions",
          "tableTo": "savings_goals",
          "columnsFrom": [
            "goal_id"
          ],
          "columnsTo": [
            "id"
          ],
          "onDelete": "cascade",
          "onUpdate": "no action"
        }
      },
      "compositePrimaryKeys": {},
      "uniqueConstraints": {},
      "policies": {},
      "checkConstraints": {},
      "isRLSEnabled": false
    },
    "public.incomes": {
      "name": "incomes",
      "schema": "",
      "columns": {
        "id": {
          "name": "id",
          "type": "text",
          "primaryKey": true,
          "notNull": true
        },
        "month_key": {
          "name": "month_key",
          "type": "text",
          "primaryKey": false,
          "notNull": true
        },
        "amount": {
          "name": "amount",
          "type": "numeric(12, 2)",
          "primaryKey": false,
          "notNull": true
        },
        "note": {
          "name": "note",
          "type": "text",
          "primaryKey": false,
          "notNull": false
        },
        "created_at": {
          "name": "created_at",
          "type": "timestamp",
          "primaryKey": false,
          "notNull": true,
          "default": "now()"
        },
        "user_id": {
          "name": "user_id",
          "type": "text",
          "primaryKey": false,
          "notNull": true
        }
      },
      "indexes": {},
      "foreignKeys": {
        "incomes_user_id_users_id_fk": {
          "name": "incomes_user_id_users_id_fk",
          "tableFrom": "incomes",
          "tableTo": "users",
          "columnsFrom": [
            "user_id"
          ],
          "columnsTo": [
            "id"
          ],
          "onDelete": "cascade",
          "onUpdate": "no action"
        }
      },
      "compositePrimaryKeys": {},
      "uniqueConstraints": {},
      "policies": {},
      "checkConstraints": {},
      "isRLSEnabled": false
    },
    "public.one_time_expenses": {
      "name": "one_time_expenses",
      "schema": "",
      "columns": {
        "id": {
          "name": "id",
          "type": "text",
          "primaryKey": true,
          "notNull": true
        },
        "month_key": {
          "name": "month_key",
          "type": "text",
          "primaryKey": false,
          "notNull": true
        },
        "name": {
          "name": "name",
          "type": "text",
          "primaryKey": false,
          "notNull": true
        },
        "amount": {
          "name": "amount",
          "type": "numeric(12, 2)",
          "primaryKey": false,
          "notNull": true
        },
        "category": {
          "name": "category",
          "type": "text",
          "primaryKey": false,
          "notNull": true
        },
        "date": {
          "name": "date",
          "type": "timestamp",
          "primaryKey": false,
          "notNull": true
        },
        "created_at": {
          "name": "created_at",
          "type": "timestamp",
          "primaryKey": false,
          "notNull": true,
          "default": "now()"
        },
        "user_id": {
          "name": "user_id",
          "type": "text",
          "primaryKey": false,
          "notNull": true
        }
      },
      "indexes": {},
      "foreignKeys": {
        "one_time_expenses_user_id_users_id_fk": {
          "name": "one_time_expenses_user_id_users_id_fk",
          "tableFrom": "one_time_expenses",
          "tableTo": "users",
          "columnsFrom": [
            "user_id"
          ],
          "columnsTo": [
            "id"
          ],
          "onDelete": "cascade",
          "onUpdate": "no action"
        }
      },
      "compositePrimaryKeys": {},
      "uniqueConstraints": {},
      "policies": {},
      "checkConstraints": {},
      "isRLSEnabled": false
    },
    "public.recurring_expenses": {
      "name": "recurring_expenses",
      "schema": "",
      "columns": {
        "id": {
          "name": "id",
          "type": "text",
          "primaryKey": true,
          "notNull": true
        },
        "name": {
          "name": "name",
          "type": "text",
          "primaryKey": false,
          "notNull": true
        },
        "amount": {
          "name": "amount",
          "type": "numeric(12, 2)",
          "primaryKey": false,
          "notNull": true
        },
        "category": {
          "name": "category",
          "type": "text",
          "primaryKey": false,
          "notNull": true
        },
        "active": {
          "name": "active",
          "type": "boolean",
          "primaryKey": false,
          "notNull": true
        },
        "start_month": {
          "name": "start_month",
          "type": "text",
          "primaryKey": false,
          "notNull": true
        },
        "created_at": {
          "name": "created_at",
          "type": "timestamp",
          "primaryKey": false,
          "notNull": true,
          "default": "now()"
        },
        "user_id": {
          "name": "user_id",
          "type": "text",
          "primaryKey": false,
          "notNull": true
        }
      },
      "indexes": {},
      "foreignKeys": {
        "recurring_expenses_user_id_users_id_fk": {
          "name": "recurring_expenses_user_id_users_id_fk",
          "tableFrom": "recurring_expenses",
          "tableTo": "users",
          "columnsFrom": [
            "user_id"
          ],
          "columnsTo": [
            "id"
          ],
          "onDelete": "cascade",
          "onUpdate": "no action"
        }
      },
      "compositePrimaryKeys": {},
      "uniqueConstraints": {},
      "policies": {},
      "checkConstraints": {},
      "isRLSEnabled": false
    },
    "public.savings_goals": {
      "name": "savings_goals",
      "schema": "",
      "columns": {
        "id": {
          "name": "id",
          "type": "text",
          "primaryKey": true,
          "notNull": true
        },
        "name": {
          "name": "name",
          "type": "text",
          "primaryKey": false,
          "notNull": true
        },
        "target_amount": {
          "name": "target_amount",
          "type": "numeric(12, 2)",
          "primaryKey": false,
          "notNull": true
        },
        "current_amount": {
          "name": "current_amount",
          "type": "numeric(12, 2)",
          "primaryKey": false,
          "notNull": true
        },
        "deadline": {
          "name": "deadline",
          "type": "timestamp",
          "primaryKey": false,
          "notNull": true
        },
        "color": {
          "name": "color",
          "type": "text",
          "primaryKey": false,
          "notNull": true
        },
        "created_at": {
          "name": "created_at",
          "type": "timestamp",
          "primaryKey": false,
          "notNull": true,
          "default": "now()"
        },
        "user_id": {
          "name": "user_id",
          "type": "text",
          "primaryKey": false,
          "notNull": true
        }
      },
      "indexes": {},
      "foreignKeys": {
        "savings_goals_user_id_users_id_fk": {
          "name": "savings_goals_user_id_users_id_fk",
          "tableFrom": "savings_goals",
          "tableTo": "users",
          "columnsFrom": [
            "user_id"
          ],
          "columnsTo": [
            "id"
          ],
          "onDelete": "cascade",
          "onUpdate": "no action"
        }
      },
      "compositePrimaryKeys": {},
      "uniqueConstraints": {},
      "policies": {},
      "checkConstraints": {},
      "isRLSEnabled": false
    },
    "public.sessions": {
      "name": "sessions",
      "schema": "",
      "columns": {
        "sessionToken": {
          "name": "sessionToken",
          "type": "text",
          "primaryKey": true,
          "notNull": true
        },
        "userId": {
          "name": "userId",
          "type": "text",
          "primaryKey": false,
          "notNull": true
        },
        "expires": {
          "name": "expires",
          "type": "timestamp",
          "primaryKey": false,
          "notNull": true
        }
      },
      "indexes": {},
      "foreignKeys": {
        "sessions_userId_users_id_fk": {
          "name": "sessions_userId_users_id_fk",
          "tableFrom": "sessions",
          "tableTo": "users",
          "columnsFrom": [
            "userId"
          ],
          "columnsTo": [
            "id"
          ],
          "onDelete": "cascade",
          "onUpdate": "no action"
        }
      },
      "compositePrimaryKeys": {},
      "uniqueConstraints": {},
      "policies": {},
      "checkConstraints": {},
      "isRLSEnabled": false
    },
    "public.users": {
      "name": "users",
      "schema": "",
      "columns": {
        "id": {
          "name": "id",
          "type": "text",
          "primaryKey": true,
          "notNull": true
        },
        "name": {
          "name": "name",
          "type": "text",
          "primaryKey": false,
          "notNull": false
        },
        "email": {
          "name": "email",
          "type": "text",
          "primaryKey": false,
          "notNull": true
        },
        "emailVerified": {
          "name": "emailVerified",
          "type": "timestamp",
          "primaryKey": false,
          "notNull": false
        },
        "image": {
          "name": "image",
          "type": "text",
          "primaryKey": false,
          "notNull": false
        },
        "password": {
          "name": "password",
          "type": "text",
          "primaryKey": false,
          "notNull": false
        },
        "created_at": {
          "name": "created_at",
          "type": "timestamp",
          "primaryKey": false,
          "notNull": true,
          "default": "now()"
        }
      },
      "indexes": {},
      "foreignKeys": {},
      "compositePrimaryKeys": {},
      "uniqueConstraints": {
        "users_email_unique": {
          "name": "users_email_unique",
          "nullsNotDistinct": false,
          "columns": [
            "email"
          ]
        }
      },
      "policies": {},
      "checkConstraints": {},
      "isRLSEnabled": false
    },
    "public.verificationTokens": {
      "name": "verificationTokens",
      "schema": "",
      "columns": {
        "identifier": {
          "name": "identifier",
          "type": "text",
          "primaryKey": false,
          "notNull": true
        },
        "token": {
          "name": "token",
          "type": "text",
          "primaryKey": false,
          "notNull": true
        },
        "expires": {
          "name": "expires",
          "type": "timestamp",
          "primaryKey": false,
          "notNull": true
        }
      },
      "indexes": {},
      "foreignKeys": {},
      "compositePrimaryKeys": {
        "verificationTokens_identifier_token_pk": {
          "name": "verificationTokens_identifier_token_pk",
          "columns": [
            "identifier",
            "token"
          ]
        }
      },
      "uniqueConstraints": {},
      "policies": {},
      "checkConstraints": {},
      "isRLSEnabled": false
    }
  },
  "enums": {},
  "schemas": {},
  "sequences": {},
  "roles": {},
  "policies": {},
  "views": {},
  "_meta": {
    "columns": {},
    "schemas": {},
    "tables": {}
  }
}